far_search_autogpt/__init__.py
far_search_autogpt/plugin.py
far_search_autogpt-1.0.0.dist-info/licenses/LICENSE
far_search_autogpt-1.0.0.dist-info/METADATA
far_search_autogpt-1.0.0.dist-info/WHEEL
far_search_autogpt-1.0.0.dist-info/top_level.txt
far_search_autogpt-1.0.0.dist-info/RECORD
