Metadata-Version: 2.4
Name: far-search-autogpt
Version: 1.0.0
Summary: AutoGPT plugin for Federal Acquisition Regulations (FAR) search
Home-page: https://github.com/blueskylineassets/far-search-tool
Author: Daniel Chang
Author-email: yschang@blueskylineassets.com
Project-URL: Homepage, https://github.com/blueskylineassets/far-search-tool
Project-URL: Documentation, https://github.com/blueskylineassets/far-search-tool#readme
Project-URL: RapidAPI, https://rapidapi.com/yschang/api/far-rag-federal-acquisition-regulation-search
Keywords: autogpt,far,federal-acquisition-regulations,government-contracting,plugin,ai-agent,compliance
Classifier: Development Status :: 4 - Beta
Classifier: Intended Audience :: Developers
Classifier: Topic :: Software Development :: Libraries :: Python Modules
Classifier: License :: OSI Approved :: MIT License
Classifier: Programming Language :: Python :: 3
Classifier: Programming Language :: Python :: 3.10
Classifier: Programming Language :: Python :: 3.11
Classifier: Programming Language :: Python :: 3.12
Requires-Python: >=3.10
License-File: LICENSE
Requires-Dist: requests>=2.28.0
Dynamic: author
Dynamic: author-email
Dynamic: classifier
Dynamic: description
Dynamic: description-content-type
Dynamic: home-page
Dynamic: keywords
Dynamic: license-file
Dynamic: project-url
Dynamic: requires-dist
Dynamic: requires-python
Dynamic: summary
